{
    "syntactic": [
        "real-world networks",
        "network topology",
        "anonymization",
        "online social networks",
        "micro-blog",
        "privacy",
        "twitter",
        "sensitive informations",
        "data privacy",
        "graph theory",
        "social networks",
        "anonymity",
        "data mining"
    ],
    "semantic": [
        "social networks",
        "online social networks",
        "data mining",
        "privacy",
        "data privacy",
        "anonymization",
        "anonymity",
        "twitter",
        "micro-blog",
        "topology",
        "network topology",
        "graph theory"
    ],
    "union": [
        "real-world networks",
        "network topology",
        "anonymization",
        "micro-blog",
        "online social networks",
        "privacy",
        "twitter",
        "sensitive informations",
        "data privacy",
        "graph theory",
        "social networks",
        "topology",
        "anonymity",
        "data mining"
    ],
    "enhanced": [
        "complex networks",
        "computer networks",
        "privacy preserving",
        "online systems",
        "computer security",
        "social media",
        "access control",
        "network security",
        "theoretical computer science",
        "world wide web",
        "authentication",
        "computer science"
    ],
    "explanation": {
        "social networks": [
            "social networking",
            "social network",
            "real world networks",
            "online social networks",
            "microblogging service",
            "twitter graph",
            "twitter",
            "microblogging",
            "anonymous twitter",
            "social networks"
        ],
        "online social networks": [
            "social networks",
            "social network",
            "online social networks"
        ],
        "sensitive informations": [
            "sensitive information"
        ],
        "data mining": [
            "mining",
            "data mining"
        ],
        "privacy": [
            "privacy",
            "data privacy",
            "anonymous",
            "sensitive information",
            "anonymity"
        ],
        "anonymization": [
            "anonymization"
        ],
        "anonymity": [
            "anonymous",
            "anonymity"
        ],
        "real-world networks": [
            "real world networks"
        ],
        "twitter": [
            "twitter graph",
            "twitter",
            "microblogging",
            "anonymous twitter",
            "microblogging service"
        ],
        "micro-blog": [
            "twitter graph",
            "twitter",
            "microblogging",
            "anonymous twitter",
            "microblogging service"
        ],
        "network topology": [
            "network topology",
            "topology"
        ],
        "data privacy": [
            "privacy",
            "data privacy"
        ],
        "graph theory": [
            "graph theory"
        ],
        "topology": [
            "network topology",
            "topology"
        ],
        "complex networks": [
            "real world networks"
        ],
        "computer networks": [
            "network topology",
            "topology"
        ],
        "privacy preserving": [
            "anonymization"
        ],
        "online systems": [
            "social networks",
            "social network",
            "online social networks"
        ],
        "computer security": [
            "privacy",
            "data privacy",
            "anonymity"
        ],
        "social media": [
            "twitter graph",
            "twitter",
            "microblogging",
            "anonymous twitter",
            "microblogging service"
        ],
        "access control": [
            "sensitive information"
        ],
        "network security": [
            "anonymous",
            "anonymity",
            "sensitive information"
        ],
        "theoretical computer science": [
            "graph theory"
        ],
        "world wide web": [
            "social networking",
            "online social networks",
            "twitter",
            "social network",
            "social networks",
            "real world networks",
            "twitter graph",
            "microblogging",
            "anonymous twitter",
            "microblogging service"
        ],
        "authentication": [
            "anonymous",
            "anonymity"
        ],
        "computer science": [
            "mining",
            "data mining"
        ]
    }
}